flake8_codes/__init__.py
flake8_codes/__main__.py
flake8_codes/_cli.py
flake8_codes/_codes/__init__.py
flake8_codes/_codes/_adhoc.py
flake8_codes/_codes/_default.py
flake8_codes/_codes/_extract.py
flake8_codes/_codes/_hardcoded.py
flake8_codes/_codes/_registry.py
flake8_codes/_codes/_renamed.py
flake8_codes/_plugins/__init__.py
flake8_codes/_plugins/_discover.py
flake8_codes/_plugins/_plugin.py
flake8_codes-0.2.2.dist-info/LICENSE
flake8_codes-0.2.2.dist-info/WHEEL
flake8_codes-0.2.2.dist-info/METADATA
flake8_codes-0.2.2.dist-info/RECORD
